{
    "name": "${CS_RULESET_NAME}",
    "labels": [],
    "rules": [
        {
            "ruleID": "TM-00000017",
            "enabled": true,
            "mitigation": "terminate"
        },
        {
            "ruleID": "TM-00000025",
            "enabled": true,
            "mitigation": "terminate"
        },
        {
            "ruleID": "TM-00000030",
            "enabled": true,
            "mitigation": "terminate"
        },
        {
            "ruleID": "TM-00000035",
            "enabled": true,
            "mitigation": "terminate"
        }
    ]
}